ssh_crypt/__init__.py
ssh_crypt/ciphers.py
ssh_crypt/constants.py
ssh_crypt/exceptions.py
ssh_crypt/jsonc_tokenizer.py
ssh_crypt/ssh_crypt.py
ssh_crypt/utils.py
ssh_crypt-1.1.12.dist-info/METADATA
ssh_crypt-1.1.12.dist-info/WHEEL
ssh_crypt-1.1.12.dist-info/entry_points.txt
ssh_crypt-1.1.12.dist-info/top_level.txt
ssh_crypt-1.1.12.dist-info/RECORD
