Metadata-Version: 2.1
Name: ssh-crypt
Version: 1.1.12
Summary: ssh-crypt is a tool to encrypt/decrypt data using your ssh key from ssh-agent
Home-page: https://github.com/Sets88/ssh-crypt
Author: Maxim Nikitenko
Author-email: iam@sets88.com
License: BSD
Platform: any
Requires-Python: >=3.5
Requires-Dist: paramiko==3.2.0
Requires-Dist: cryptography==40.0.2
